strands_agents_samples/__init__.py
strands_agents_samples/main.py
strands_agents_samples-0.0.1.dist-info/METADATA
strands_agents_samples-0.0.1.dist-info/WHEEL
strands_agents_samples-0.0.1.dist-info/RECORD
